benchmarks/__init__.py
benchmarks/benchmark_runner.py
benchmarks/mutation_benchmark.py
benchmarks/web_backend_test.py
docs/source/conf.py
examples/ligand_aware_folding_demo.py
examples/mutation_prediction_demo.py
examples/mutation_scanning_demo.py
experiments/test_templates_openfold.py
odinfold-1.0.0a8.dist-info/licenses/LICENSE
openfold/__init__.py
openfold/config.py
openfold/benchmarks/comprehensive_benchmark.py
openfold/cuda_kernels/setup.py
openfold/model/__init__.py
openfold/model/cuda_kernels_interface.py
openfold/model/cuda_triangle_ops.py
openfold/model/delta_predictor.py
openfold/model/dropout.py
openfold/model/embedders.py
openfold/model/evoformer.py
openfold/model/heads.py
openfold/model/ligand_integration.py
openfold/model/model.py
openfold/model/msa.py
openfold/model/outer_product_mean.py
openfold/model/pair_transition.py
openfold/model/primitives.py
openfold/model/structure_module.py
openfold/model/template.py
openfold/model/torchscript.py
openfold/model/triangular_attention.py
openfold/model/triangular_multiplicative_update.py
openfold/np/__init__.py
openfold/np/protein.py
openfold/np/residue_constants.py
openfold/np/relax/__init__.py
openfold/np/relax/amber_minimize.py
openfold/np/relax/cleanup.py
openfold/np/relax/relax.py
openfold/np/relax/utils.py
openfold/services/mutation_with_refinement.py
openfold/services/optimized_mutation_server.py
openfold/services/websocket_server.py
openfold/training/delta_trainer.py
openfold/utils/__init__.py
openfold/utils/all_atom_multimer.py
openfold/utils/argparse_utils.py
openfold/utils/callbacks.py
openfold/utils/checkpointing.py
openfold/utils/chunk_utils.py
openfold/utils/exponential_moving_average.py
openfold/utils/feats.py
openfold/utils/gpu_memory_optimization.py
openfold/utils/import_weights.py
openfold/utils/logger.py
openfold/utils/loss.py
openfold/utils/lr_schedulers.py
openfold/utils/md_refinement.py
openfold/utils/mmseqs2_integration.py
openfold/utils/multi_chain_permutation.py
openfold/utils/precision_utils.py
openfold/utils/quantization.py
odinfold-1.0.0a8.dist-info/METADATA
odinfold-1.0.0a8.dist-info/WHEEL
odinfold-1.0.0a8.dist-info/top_level.txt
odinfold-1.0.0a8.dist-info/RECORD
