Metadata-Version: 2.4
Name: odinfold
Version: 1.0.0a8
Summary: OdinFold - The engine that powers FoldForever
Home-page: https://github.com/euticus/openfold
Author: OdinFold Team
Author-email: OdinFold Team <team@odinfold.ai>
Classifier: Development Status :: 4 - Beta
Classifier: Intended Audience :: Science/Research
Classifier: License :: OSI Approved :: Apache Software License
Classifier: Programming Language :: Python :: 3
Classifier: Programming Language :: Python :: 3.9
Classifier: Programming Language :: Python :: 3.10
Classifier: Programming Language :: Python :: 3.11
Classifier: Topic :: Scientific/Engineering :: Bio-Informatics
Requires-Python: >=3.9
License-File: LICENSE
Dynamic: author
Dynamic: home-page
Dynamic: license-file
Dynamic: requires-python
